{
  "id": "ca73293c-3af3-4bab-a5dc-f8b485a06ecf",
  "prevId": "b4983789-c18e-4f7e-aaea-a0ba53017bf9",
  "version": "7",
  "dialect": "postgresql",
  "tables": {
    "public.activity_logs": {
      "name": "activity_logs",
      "schema": "",
      "columns": {
        "id": {
          "name": "id",
          "type": "serial",
          "primaryKey": true,
          "notNull": true
        },
        "user_id": {
          "name": "user_id",
          "type": "integer",
          "primaryKey": false,
          "notNull": false
        },
        "action_type": {
          "name": "action_type",
          "type": "action_type",
          "typeSchema": "public",
          "primaryKey": false,
          "notNull": true
        },
        "description": {
          "name": "description",
          "type": "text",
          "primaryKey": false,
          "notNull": false
        },
        "ip_address": {
          "name": "ip_address",
          "type": "varchar(50)",
          "primaryKey": false,
          "notNull": false
        },
        "created_at": {
          "name": "created_at",
          "type": "timestamp",
          "primaryKey": false,
          "notNull": false,
          "default": "now()"
        }
      },
      "indexes": {},
      "foreignKeys": {
        "activity_logs_user_id_users_id_fk": {
          "name": "activity_logs_user_id_users_id_fk",
          "tableFrom": "activity_logs",
          "tableTo": "users",
          "columnsFrom": [
            "user_id"
          ],
          "columnsTo": [
            "id"
          ],
          "onDelete": "no action",
          "onUpdate": "no action"
        }
      },
      "compositePrimaryKeys": {},
      "uniqueConstraints": {},
      "policies": {},
      "checkConstraints": {},
      "isRLSEnabled": false
    },
    "public.ambulances": {
      "name": "ambulances",
      "schema": "",
      "columns": {
        "id": {
          "name": "id",
          "type": "serial",
          "primaryKey": true,
          "notNull": true
        },
        "hospital_id": {
          "name": "hospital_id",
          "type": "integer",
          "primaryKey": false,
          "notNull": true
        },
        "plate_number": {
          "name": "plate_number",
          "type": "varchar(20)",
          "primaryKey": false,
          "notNull": true
        },
        "driver_id": {
          "name": "driver_id",
          "type": "integer",
          "primaryKey": false,
          "notNull": false
        },
        "status": {
          "name": "status",
          "type": "ambulance_status",
          "typeSchema": "public",
          "primaryKey": false,
          "notNull": true,
          "default": "'available'"
        },
        "created_at": {
          "name": "created_at",
          "type": "timestamp",
          "primaryKey": false,
          "notNull": false,
          "default": "now()"
        }
      },
      "indexes": {},
      "foreignKeys": {
        "ambulances_hospital_id_hospitals_id_fk": {
          "name": "ambulances_hospital_id_hospitals_id_fk",
          "tableFrom": "ambulances",
          "tableTo": "hospitals",
          "columnsFrom": [
            "hospital_id"
          ],
          "columnsTo": [
            "id"
          ],
          "onDelete": "cascade",
          "onUpdate": "no action"
        },
        "ambulances_driver_id_users_id_fk": {
          "name": "ambulances_driver_id_users_id_fk",
          "tableFrom": "ambulances",
          "tableTo": "users",
          "columnsFrom": [
            "driver_id"
          ],
          "columnsTo": [
            "id"
          ],
          "onDelete": "set null",
          "onUpdate": "no action"
        }
      },
      "compositePrimaryKeys": {},
      "uniqueConstraints": {
        "ambulances_plate_number_unique": {
          "name": "ambulances_plate_number_unique",
          "nullsNotDistinct": false,
          "columns": [
            "plate_number"
          ]
        }
      },
      "policies": {},
      "checkConstraints": {},
      "isRLSEnabled": false
    },
    "public.emergency_requests": {
      "name": "emergency_requests",
      "schema": "",
      "columns": {
        "id": {
          "name": "id",
          "type": "serial",
          "primaryKey": true,
          "notNull": true
        },
        "patient_id": {
          "name": "patient_id",
          "type": "integer",
          "primaryKey": false,
          "notNull": true
        },
        "hospital_id": {
          "name": "hospital_id",
          "type": "integer",
          "primaryKey": false,
          "notNull": false
        },
        "ambulance_id": {
          "name": "ambulance_id",
          "type": "integer",
          "primaryKey": false,
          "notNull": false
        },
        "emergency_level": {
          "name": "emergency_level",
          "type": "emergency_level",
          "typeSchema": "public",
          "primaryKey": false,
          "notNull": true
        },
        "description": {
          "name": "description",
          "type": "text",
          "primaryKey": false,
          "notNull": false
        },
        "latitude": {
          "name": "latitude",
          "type": "varchar(50)",
          "primaryKey": false,
          "notNull": true
        },
        "longitude": {
          "name": "longitude",
          "type": "varchar(50)",
          "primaryKey": false,
          "notNull": true
        },
        "status": {
          "name": "status",
          "type": "varchar(50)",
          "primaryKey": false,
          "notNull": false,
          "default": "'pending'"
        },
        "created_at": {
          "name": "created_at",
          "type": "timestamp",
          "primaryKey": false,
          "notNull": false,
          "default": "now()"
        }
      },
      "indexes": {},
      "foreignKeys": {
        "emergency_requests_patient_id_users_id_fk": {
          "name": "emergency_requests_patient_id_users_id_fk",
          "tableFrom": "emergency_requests",
          "tableTo": "users",
          "columnsFrom": [
            "patient_id"
          ],
          "columnsTo": [
            "id"
          ],
          "onDelete": "cascade",
          "onUpdate": "no action"
        },
        "emergency_requests_hospital_id_hospitals_id_fk": {
          "name": "emergency_requests_hospital_id_hospitals_id_fk",
          "tableFrom": "emergency_requests",
          "tableTo": "hospitals",
          "columnsFrom": [
            "hospital_id"
          ],
          "columnsTo": [
            "id"
          ],
          "onDelete": "cascade",
          "onUpdate": "no action"
        },
        "emergency_requests_ambulance_id_ambulances_id_fk": {
          "name": "emergency_requests_ambulance_id_ambulances_id_fk",
          "tableFrom": "emergency_requests",
          "tableTo": "ambulances",
          "columnsFrom": [
            "ambulance_id"
          ],
          "columnsTo": [
            "id"
          ],
          "onDelete": "set null",
          "onUpdate": "no action"
        }
      },
      "compositePrimaryKeys": {},
      "uniqueConstraints": {},
      "policies": {},
      "checkConstraints": {},
      "isRLSEnabled": false
    },
    "public.hospital_admins": {
      "name": "hospital_admins",
      "schema": "",
      "columns": {
        "id": {
          "name": "id",
          "type": "serial",
          "primaryKey": true,
          "notNull": true
        },
        "user_id": {
          "name": "user_id",
          "type": "integer",
          "primaryKey": false,
          "notNull": true
        },
        "hospital_id": {
          "name": "hospital_id",
          "type": "integer",
          "primaryKey": false,
          "notNull": true
        }
      },
      "indexes": {},
      "foreignKeys": {
        "hospital_admins_user_id_users_id_fk": {
          "name": "hospital_admins_user_id_users_id_fk",
          "tableFrom": "hospital_admins",
          "tableTo": "users",
          "columnsFrom": [
            "user_id"
          ],
          "columnsTo": [
            "id"
          ],
          "onDelete": "cascade",
          "onUpdate": "no action"
        },
        "hospital_admins_hospital_id_hospitals_id_fk": {
          "name": "hospital_admins_hospital_id_hospitals_id_fk",
          "tableFrom": "hospital_admins",
          "tableTo": "hospitals",
          "columnsFrom": [
            "hospital_id"
          ],
          "columnsTo": [
            "id"
          ],
          "onDelete": "cascade",
          "onUpdate": "no action"
        }
      },
      "compositePrimaryKeys": {},
      "uniqueConstraints": {},
      "policies": {},
      "checkConstraints": {},
      "isRLSEnabled": false
    },
    "public.hospitals": {
      "name": "hospitals",
      "schema": "",
      "columns": {
        "id": {
          "name": "id",
          "type": "serial",
          "primaryKey": true,
          "notNull": true
        },
        "name": {
          "name": "name",
          "type": "varchar(200)",
          "primaryKey": false,
          "notNull": true
        },
        "address": {
          "name": "address",
          "type": "text",
          "primaryKey": false,
          "notNull": false
        },
        "latitude": {
          "name": "latitude",
          "type": "varchar(50)",
          "primaryKey": false,
          "notNull": false
        },
        "longitude": {
          "name": "longitude",
          "type": "varchar(50)",
          "primaryKey": false,
          "notNull": false
        },
        "phone": {
          "name": "phone",
          "type": "varchar(20)",
          "primaryKey": false,
          "notNull": false
        },
        "email": {
          "name": "email",
          "type": "varchar(150)",
          "primaryKey": false,
          "notNull": false
        },
        "is_public": {
          "name": "is_public",
          "type": "boolean",
          "primaryKey": false,
          "notNull": false,
          "default": true
        },
        "created_at": {
          "name": "created_at",
          "type": "timestamp",
          "primaryKey": false,
          "notNull": false,
          "default": "now()"
        }
      },
      "indexes": {},
      "foreignKeys": {},
      "compositePrimaryKeys": {},
      "uniqueConstraints": {},
      "policies": {},
      "checkConstraints": {},
      "isRLSEnabled": false
    },
    "public.penalties": {
      "name": "penalties",
      "schema": "",
      "columns": {
        "id": {
          "name": "id",
          "type": "serial",
          "primaryKey": true,
          "notNull": true
        },
        "user_id": {
          "name": "user_id",
          "type": "integer",
          "primaryKey": false,
          "notNull": true
        },
        "reason": {
          "name": "reason",
          "type": "text",
          "primaryKey": false,
          "notNull": true
        },
        "count": {
          "name": "count",
          "type": "integer",
          "primaryKey": false,
          "notNull": false,
          "default": 1
        },
        "created_at": {
          "name": "created_at",
          "type": "timestamp",
          "primaryKey": false,
          "notNull": false,
          "default": "now()"
        }
      },
      "indexes": {},
      "foreignKeys": {
        "penalties_user_id_users_id_fk": {
          "name": "penalties_user_id_users_id_fk",
          "tableFrom": "penalties",
          "tableTo": "users",
          "columnsFrom": [
            "user_id"
          ],
          "columnsTo": [
            "id"
          ],
          "onDelete": "cascade",
          "onUpdate": "no action"
        }
      },
      "compositePrimaryKeys": {},
      "uniqueConstraints": {},
      "policies": {},
      "checkConstraints": {},
      "isRLSEnabled": false
    },
    "public.trips": {
      "name": "trips",
      "schema": "",
      "columns": {
        "id": {
          "name": "id",
          "type": "serial",
          "primaryKey": true,
          "notNull": true
        },
        "request_id": {
          "name": "request_id",
          "type": "integer",
          "primaryKey": false,
          "notNull": true
        },
        "ambulance_id": {
          "name": "ambulance_id",
          "type": "integer",
          "primaryKey": false,
          "notNull": true
        },
        "driver_id": {
          "name": "driver_id",
          "type": "integer",
          "primaryKey": false,
          "notNull": true
        },
        "status": {
          "name": "status",
          "type": "trip_status",
          "typeSchema": "public",
          "primaryKey": false,
          "notNull": true,
          "default": "'pending'"
        },
        "started_at": {
          "name": "started_at",
          "type": "timestamp",
          "primaryKey": false,
          "notNull": false
        },
        "ended_at": {
          "name": "ended_at",
          "type": "timestamp",
          "primaryKey": false,
          "notNull": false
        },
        "updated_at": {
          "name": "updated_at",
          "type": "timestamp",
          "primaryKey": false,
          "notNull": false,
          "default": "now()"
        }
      },
      "indexes": {},
      "foreignKeys": {
        "trips_request_id_emergency_requests_id_fk": {
          "name": "trips_request_id_emergency_requests_id_fk",
          "tableFrom": "trips",
          "tableTo": "emergency_requests",
          "columnsFrom": [
            "request_id"
          ],
          "columnsTo": [
            "id"
          ],
          "onDelete": "cascade",
          "onUpdate": "no action"
        },
        "trips_ambulance_id_ambulances_id_fk": {
          "name": "trips_ambulance_id_ambulances_id_fk",
          "tableFrom": "trips",
          "tableTo": "ambulances",
          "columnsFrom": [
            "ambulance_id"
          ],
          "columnsTo": [
            "id"
          ],
          "onDelete": "cascade",
          "onUpdate": "no action"
        },
        "trips_driver_id_users_id_fk": {
          "name": "trips_driver_id_users_id_fk",
          "tableFrom": "trips",
          "tableTo": "users",
          "columnsFrom": [
            "driver_id"
          ],
          "columnsTo": [
            "id"
          ],
          "onDelete": "cascade",
          "onUpdate": "no action"
        }
      },
      "compositePrimaryKeys": {},
      "uniqueConstraints": {},
      "policies": {},
      "checkConstraints": {},
      "isRLSEnabled": false
    },
    "public.users": {
      "name": "users",
      "schema": "",
      "columns": {
        "id": {
          "name": "id",
          "type": "serial",
          "primaryKey": true,
          "notNull": true
        },
        "full_name": {
          "name": "full_name",
          "type": "varchar(100)",
          "primaryKey": false,
          "notNull": true
        },
        "email": {
          "name": "email",
          "type": "varchar(150)",
          "primaryKey": false,
          "notNull": true
        },
        "phone": {
          "name": "phone",
          "type": "varchar(20)",
          "primaryKey": false,
          "notNull": true
        },
        "password_hash": {
          "name": "password_hash",
          "type": "text",
          "primaryKey": false,
          "notNull": true
        },
        "role": {
          "name": "role",
          "type": "user_role",
          "typeSchema": "public",
          "primaryKey": false,
          "notNull": true,
          "default": "'patient'"
        },
        "national_id": {
          "name": "national_id",
          "type": "varchar(20)",
          "primaryKey": false,
          "notNull": false
        },
        "status": {
          "name": "status",
          "type": "user_status",
          "typeSchema": "public",
          "primaryKey": false,
          "notNull": true,
          "default": "'active'"
        },
        "created_at": {
          "name": "created_at",
          "type": "timestamp",
          "primaryKey": false,
          "notNull": false,
          "default": "now()"
        }
      },
      "indexes": {},
      "foreignKeys": {},
      "compositePrimaryKeys": {},
      "uniqueConstraints": {
        "users_email_unique": {
          "name": "users_email_unique",
          "nullsNotDistinct": false,
          "columns": [
            "email"
          ]
        },
        "users_phone_unique": {
          "name": "users_phone_unique",
          "nullsNotDistinct": false,
          "columns": [
            "phone"
          ]
        },
        "users_national_id_unique": {
          "name": "users_national_id_unique",
          "nullsNotDistinct": false,
          "columns": [
            "national_id"
          ]
        }
      },
      "policies": {},
      "checkConstraints": {},
      "isRLSEnabled": false
    }
  },
  "enums": {
    "public.action_type": {
      "name": "action_type",
      "schema": "public",
      "values": [
        "login",
        "logout",
        "user_create",
        "user_update",
        "user_delete",
        "user_read",
        "hospital_create",
        "hospital_update",
        "hospital_delete",
        "hospital_admin_create",
        "hospital_admin_update",
        "hospital_admin_delete",
        "ambulance_create",
        "ambulance_update",
        "ambulance_delete",
        "emergency_request_create",
        "emergency_request_update",
        "emergency_request_delete",
        "trip_create",
        "trip_update",
        "trip_delete",
        "trip_cancel",
        "penalty_create",
        "penalty_update",
        "penalty_delete",
        "joker_detected",
        "other"
      ]
    },
    "public.ambulance_status": {
      "name": "ambulance_status",
      "schema": "public",
      "values": [
        "available",
        "on_trip",
        "unavailable"
      ]
    },
    "public.emergency_level": {
      "name": "emergency_level",
      "schema": "public",
      "values": [
        "critical",
        "urgent",
        "non_urgent"
      ]
    },
    "public.trip_status": {
      "name": "trip_status",
      "schema": "public",
      "values": [
        "pending",
        "en_route",
        "picked_up",
        "arrived",
        "cancelled"
      ]
    },
    "public.user_role": {
      "name": "user_role",
      "schema": "public",
      "values": [
        "patient",
        "ambulance_driver",
        "hospital_admin",
        "system_admin"
      ]
    },
    "public.user_status": {
      "name": "user_status",
      "schema": "public",
      "values": [
        "active",
        "deactivated",
        "blacklisted"
      ]
    }
  },
  "schemas": {},
  "sequences": {},
  "roles": {},
  "policies": {},
  "views": {},
  "_meta": {
    "columns": {},
    "schemas": {},
    "tables": {}
  }
}